[{"name":"Hotel D","stars":5,"rooms":[{"code":"SNGRM","net_price":"200.00","taxes":{"amount":"15.00","currency":"EUR","type":"TAXESANDFEES"},"total":"215.00"},{"code":"FU-BOD","net_price":"120.00","taxes":{"amount":"16.00","currency":"EUR","type":"TAXESANDFEES"},"total":"136.00"},{"code":"POAROM","net_price":"105.00","taxes":{"amount":"14.00","currency":"EUR","type":"TAXESANDFEES"},"total":"119.00"}]},{"name":"Hotel A","stars":4,"rooms":[{"code":"DBL-TWN","name":"Double or Twin SUPERIOR","net_rate":"140.00","taxes":[{"amount":"10.00","currency":"EUR","type":"TAXESANDFEES"}],"totalPrice":"150.00"},{"code":"HF-BD","name":"HALF BOARD","net_rate":"130.00","taxes":[{"amount":"11.00","currency":"EUR","type":"TAXESANDFEES"}],"totalPrice":"141.00"},{"code":"QN-RM","name":"Queen Room","net_rate":"160","taxes":[{"amount":"12.00","currency":"EUR","type":"TAXESANDFEES"},{"amount":"4.00","currency":"EUR","type":"EXTRA_FEES"}],"totalPrice":"176.00"}]},{"name":"Hotel B","stars":5,"rooms":[{"code":"DBL-RM","name":"Double Room","net_rate":"110.00","taxes":[{"amount":"15.00","currency":"EUR","type":"TAXESANDFEES"}],"totalPrice":"125.00"},{"code":"HF-BOD","name":"HALF BOARD","net_rate":"140.00","taxes":[{"amount":"8.00","currency":"EUR","type":"TAXESANDFEES"},{"amount":"4.00","currency":"EUR","type":"EXTRA_FEES"}],"totalPrice":"152.00"},{"code":"QUN-ROM","name":"Queen Room","net_rate":"110.00","taxes":[{"amount":"6.50","currency":"EUR","type":"EXTRA_FEES"}],"totalPrice":"116.50"}]},{"name":"Hotel C","stars":5,"rooms":[{"code":"SNG-RM","name":"Single Bed","net_rate":"80.00","taxes":[{"amount":"12.00","currency":"EUR","type":"TAXESANDFEES"}],"totalPrice":"92.00"},{"code":"FUBOD","name":"FULL BOARD","net_rate":"165.00","taxes":[{"amount":"15.00","currency":"EUR","type":"TAXESANDFEES"}],"totalPrice":"180.00"},{"code":"LUX-ROM","name":"Luxury Room","net_rate":"155.00","taxes":[{"amount":"22.00","currency":"EUR","type":"TAXESANDFEES"}],"totalPrice":"177.00"}]}]